moneymour/__init__.py
moneymour/api_client.py
moneymour/crypto_utils.py
moneymour/environments.py
test/__init__.py
test/moneymour/__init__.py
test/moneymour/integration/__init__.py
test/moneymour/integration/api_client_test.py
test/moneymour/unit/__init__.py
test/moneymour/unit/crypto_utils_test.py
moneymour_api_client-0.0.2.dist-info/LICENSE
moneymour_api_client-0.0.2.dist-info/METADATA
moneymour_api_client-0.0.2.dist-info/WHEEL
moneymour_api_client-0.0.2.dist-info/top_level.txt
moneymour_api_client-0.0.2.dist-info/RECORD
