Metadata-Version: 2.1
Name: moneymour-api-client
Version: 0.0.2
Summary: The library offers easy access to Moneymour APIs
Home-page: https://github.com/moneymour/api-client-python
Author: Antonio Trapani
Author-email: antonio.trapani@gmail.com
License: UNKNOWN
Platform: UNKNOWN
Classifier: Programming Language :: Python :: 3
Classifier: License :: OSI Approved :: Apache Software License
Classifier: Operating System :: OS Independent
Requires-Python: >=3.7
Requires-Dist: requests
Requires-Dist: pycrypto
